django_fast_count/__init__.py
django_fast_count/managers.py
django_fast_count/models.py
django_fast_count/management/__init__.py
django_fast_count/management/commands/__init__.py
django_fast_count/management/commands/precache_fast_counts.py
django_fast_count/migrations/0001_initial.py
django_fast_count/migrations/__init__.py
django_fast_count-0.1.11.dist-info/licenses/LICENSE
tests/__init__.py
tests/djangotest/__init__.py
tests/djangotest/manage.py
tests/djangotest/djangotest/__init__.py
tests/djangotest/djangotest/asgi.py
tests/djangotest/djangotest/settings.py
tests/djangotest/djangotest/urls.py
tests/djangotest/djangotest/wsgi.py
tests/djangotest/testapp/__init__.py
tests/djangotest/testapp/admin.py
tests/djangotest/testapp/apps.py
tests/djangotest/testapp/managers.py
tests/djangotest/testapp/models.py
tests/djangotest/testapp/views.py
tests/djangotest/testapp/migrations/0001_initial.py
tests/djangotest/testapp/migrations/0002_alter_testmodel_flag.py
tests/djangotest/testapp/migrations/0003_anothertestmodel_modelwithbadfastcountquerysets_and_more.py
tests/djangotest/testapp/migrations/0004_modelwithdeepmanager_modelwithintermediatemanager.py
tests/djangotest/testapp/migrations/__init__.py
tests/djangotest/testapp/tests/__init__.py
tests/djangotest/testapp/tests/test_coverage_improvements.py
tests/djangotest/testapp/tests/test_django_fast_count.py
tests/djangotest/testapp/tests/test_edge_cases_and_errors.py
tests/djangotest/testapp/tests/test_manager_inheritance.py
django_fast_count-0.1.11.dist-info/METADATA
django_fast_count-0.1.11.dist-info/WHEEL
django_fast_count-0.1.11.dist-info/top_level.txt
django_fast_count-0.1.11.dist-info/RECORD
