Metadata-Version: 2.4
Name: django-fast-count
Version: 0.1.11
Summary: A fast Django .count() implementation for large tables.
Home-page: https://github.com/curvedinf/django-fast-count
Author: Chase Adams
Author-email: chase.adams@gmail.com
License: MIT
Classifier: Programming Language :: Python :: 3
Classifier: License :: OSI Approved :: MIT License
Classifier: Operating System :: OS Independent
Requires-Python: >=3.6
License-File: LICENSE
Requires-Dist: django>=3.2
Dynamic: author
Dynamic: author-email
Dynamic: classifier
Dynamic: description
Dynamic: description-content-type
Dynamic: home-page
Dynamic: license
Dynamic: license-file
Dynamic: requires-dist
Dynamic: requires-python
Dynamic: summary
